dps_mysql_ha_sdk/__init__.py
dps_mysql_ha_sdk/dynamic_pooled_db.py
dps_mysql_ha_sdk/db/__init__.py
dps_mysql_ha_sdk/db/db_utils.py
dps_mysql_ha_sdk/db/dss_utils.py
dps_mysql_ha_sdk/db/http_utils.py
dps_mysql_ha_sdk/db/test_db.py
dps_mysql_ha_sdk/utils/__init__.py
dps_mysql_ha_sdk/utils/check_utils.py
dps_mysql_ha_sdk/utils/log_utils.py
dps_mysql_ha_sdk-1.11.dist-info/METADATA
dps_mysql_ha_sdk-1.11.dist-info/WHEEL
dps_mysql_ha_sdk-1.11.dist-info/top_level.txt
dps_mysql_ha_sdk-1.11.dist-info/RECORD
