Metadata-Version: 2.1
Name: dps-mysql-ha-sdk
Version: 1.11
Summary: 高可用数据库连接
Author: daijiacong
License: MIT
